nbquarto/__init__.py
nbquarto/cli.py
nbquarto/foundation.py
nbquarto/imports.py
nbquarto/notebook.py
nbquarto/process.py
nbquarto/processor.py
nbquarto/utils.py
nbquarto/processors/__init__.py
nbquarto/processors/autodoc.py
nbquarto/processors/codenotes.py
nbquarto/processors/codenotes_v2.py
nbquarto/processors/example.py
nbquarto-0.0.1.dist-info/LICENSE
nbquarto-0.0.1.dist-info/METADATA
nbquarto-0.0.1.dist-info/WHEEL
nbquarto-0.0.1.dist-info/entry_points.txt
nbquarto-0.0.1.dist-info/top_level.txt
nbquarto-0.0.1.dist-info/RECORD
