Metadata-Version: 2.1
Name: nbquarto
Version: 0.0.1
Summary: A minimal nbdev version, focused on writing quarto extensions
Home-page: https://github.com/muellerzr/nbquarto
Author: Zachary Mueller
License: MIT
Keywords: quarto
Classifier: Development Status :: 3 - Alpha
Classifier: Intended Audience :: Developers
Classifier: Framework :: Jupyter
Classifier: License :: OSI Approved :: MIT License
Classifier: Programming Language :: Python :: 3.7
Requires-Python: >=3.7
License-File: LICENSE
Requires-Dist: pyyaml
Requires-Dist: hf-doc-builder (~=0.4.0)
Provides-Extra: quality
Requires-Dist: black (~=23.1) ; extra == 'quality'
Requires-Dist: ruff (>=0.0.241) ; extra == 'quality'
Provides-Extra: testing
Requires-Dist: pytest ; extra == 'testing'
Requires-Dist: black (~=23.1) ; extra == 'testing'
Requires-Dist: ruff (>=0.0.241) ; extra == 'testing'
